{
  "version": "1.0",
  "defaultProvider": "cdnjs",
  "libraries": [
    {
      "library": "admin-lte@3.2.0",
      "destination": "wwwroot/lib/admin-lte/"
    },
    {
      "library": "select2@4.0.13",
      "destination": "wwwroot/lib/select2/"
    },
    {
      "library": "datatables@1.10.21",
      "destination": "wwwroot/lib/datatables/"
    },
    {
      "library": "sweetalert2@11.7.3",
      "destination": "wwwroot/lib/sweetalert2/"
    },
    {
      "library": "font-awesome@6.4.0",
      "destination": "wwwroot/lib/font-awesome/"
    }
  ]
}